.coveragerc
.travis.yml
LICENSE
MANIFEST.in
README.rst
setup.cfg
setup.py
Mopidy_Bassdrive.egg-info/PKG-INFO
Mopidy_Bassdrive.egg-info/SOURCES.txt
Mopidy_Bassdrive.egg-info/dependency_links.txt
Mopidy_Bassdrive.egg-info/entry_points.txt
Mopidy_Bassdrive.egg-info/not-zip-safe
Mopidy_Bassdrive.egg-info/requires.txt
Mopidy_Bassdrive.egg-info/top_level.txt
mopidy_bassdrive/__init__.py
mopidy_bassdrive/actor.py
mopidy_bassdrive/ext.conf
mopidy_bassdrive/library.py
tests/__init__.py
tests/test_extension.py
tests/test_extension_backend.py