Metadata-Version: 1.1
Name: Mopidy-Bassdrive
Version: 0.2.0
Summary: Bassdrive archive and stream extension for Mopidy
Home-page: http://github.com/felixb/mopidy-bassdrive/
Author: Felix Bechstein
Author-email: f@ub0r.de
License: Apache License, Version 2.0
Platform: UNKNOWN
Classifier: Environment :: No Input/Output (Daemon)
Classifier: Intended Audience :: End Users/Desktop
Classifier: License :: OSI Approved :: MIT License
Classifier: Operating System :: OS Independent
Classifier: Programming Language :: Python :: 2
Classifier: Topic :: Multimedia :: Sound/Audio :: Players
